MANIFEST.in
README.rst
setup.cfg
setup.py
docs/CREDITS.rst
docs/HISTORY.rst
docs/LICENSE.GPL
docs/LICENSE.txt
src/sc/__init__.py
src/sc.contentrules.layout.egg-info/PKG-INFO
src/sc.contentrules.layout.egg-info/SOURCES.txt
src/sc.contentrules.layout.egg-info/dependency_links.txt
src/sc.contentrules.layout.egg-info/entry_points.txt
src/sc.contentrules.layout.egg-info/namespace_packages.txt
src/sc.contentrules.layout.egg-info/not-zip-safe
src/sc.contentrules.layout.egg-info/requires.txt
src/sc.contentrules.layout.egg-info/top_level.txt
src/sc/contentrules/__init__.py
src/sc/contentrules/layout/__init__.py
src/sc/contentrules/layout/config.py
src/sc/contentrules/layout/configure.zcml
src/sc/contentrules/layout/interfaces.py
src/sc/contentrules/layout/testing.py
src/sc/contentrules/layout/vocabulary.py
src/sc/contentrules/layout/actions/__init__.py
src/sc/contentrules/layout/actions/layout.py
src/sc/contentrules/layout/locales/manual.pot
src/sc/contentrules/layout/locales/plone.pot
src/sc/contentrules/layout/locales/sc.contentrules.layout.pot
src/sc/contentrules/layout/locales/en/LC_MESSAGES/plone.mo
src/sc/contentrules/layout/locales/en/LC_MESSAGES/plone.po
src/sc/contentrules/layout/locales/en/LC_MESSAGES/sc.contentrules.layout.mo
src/sc/contentrules/layout/locales/en/LC_MESSAGES/sc.contentrules.layout.po
src/sc/contentrules/layout/locales/es/LC_MESSAGES/plone.mo
src/sc/contentrules/layout/locales/es/LC_MESSAGES/plone.po
src/sc/contentrules/layout/locales/es/LC_MESSAGES/sc.contentrules.layout.mo
src/sc/contentrules/layout/locales/es/LC_MESSAGES/sc.contentrules.layout.po
src/sc/contentrules/layout/locales/pt_BR/LC_MESSAGES/plone.mo
src/sc/contentrules/layout/locales/pt_BR/LC_MESSAGES/plone.po
src/sc/contentrules/layout/locales/pt_BR/LC_MESSAGES/sc.contentrules.layout.mo
src/sc/contentrules/layout/locales/pt_BR/LC_MESSAGES/sc.contentrules.layout.po
src/sc/contentrules/layout/tests/__init__.py
src/sc/contentrules/layout/tests/control_panel.txt
src/sc/contentrules/layout/tests/test_action.py
src/sc/contentrules/layout/tests/test_functional.py