Metadata-Version: 1.1
Name: sc.contentrules.layout
Version: 1.0.1
Summary: Content Rules Action: Set layout for a content item
Home-page: http://www.simplesconsultoria.com.br/
Author: Simples Consultoria
Author-email: products@simplesconsultoria.com.br
License: GPLv2
Keywords: plone contentrules action
Platform: UNKNOWN
Classifier: Development Status :: 4 - Beta
Classifier: Environment :: Web Environment
Classifier: Framework :: Plone
Classifier: Framework :: Plone :: 4.2
Classifier: Framework :: Plone :: 4.3
Classifier: Intended Audience :: Developers
Classifier: License :: OSI Approved :: GNU General Public License v2 (GPLv2)
Classifier: Operating System :: OS Independent
Classifier: Programming Language :: Python
Classifier: Programming Language :: Python :: 2.6
Classifier: Programming Language :: Python :: 2.7
Classifier: Topic :: Internet :: WWW/HTTP
Classifier: Topic :: Internet :: WWW/HTTP :: Dynamic Content
Classifier: Topic :: Software Development :: Libraries :: Python Modules
